stac_collection_search/__init__.py
stac_collection_search/utils.py
stac_collection_search-0.1.1.dist-info/LICENSE.md
stac_collection_search-0.1.1.dist-info/METADATA
stac_collection_search-0.1.1.dist-info/WHEEL
stac_collection_search-0.1.1.dist-info/top_level.txt
stac_collection_search-0.1.1.dist-info/RECORD
