Metadata-Version: 2.1
Name: stac-collection-search
Version: 0.1.1
Summary: STAC Collection Search helper utility
Author: Ivica Matic
Author-email: <ivica.matic@spatialdays.com>
Keywords: python,azure,stac,fastapi,eo,earth observation,spatial,search,collection
Classifier: Development Status :: 1 - Planning
Classifier: Intended Audience :: Developers
Classifier: Programming Language :: Python :: 3
Classifier: Operating System :: Unix
License-File: LICENSE.md
Requires-Dist: certifi >=2023.5.7
Requires-Dist: charset-normalizer >=3.1.0
Requires-Dist: idna >=3.4
Requires-Dist: numpy >=1.25.0
Requires-Dist: requests >=2.31.0
Requires-Dist: shapely >=2.0.1
Requires-Dist: urllib3 >=2.0.3
